{
  "ticker": "CF",
  "name": "CF Industries Holdings, Inc.",
  "cik": 1324404,
  "fiscalYear": 2025,
  "metrics": {
    "revenue": {
      "value": 7084000000,
      "year": 2025,
      "periodEnd": "2025-12-31"
    },
    "cogs": {
      "value": 4360000000,
      "year": 2025,
      "periodEnd": "2025-12-31"
    },
    "grossProfit": {
      "value": 2724000000,
      "year": 2025,
      "periodEnd": "2025-12-31"
    },
    "operatingIncome": {
      "value": 2300000000,
      "year": 2025,
      "periodEnd": "2025-12-31"
    },
    "netIncome": {
      "value": 1539200000,
      "year": 2011,
      "periodEnd": "2011-12-31"
    },
    "currentAssets": {
      "value": 2985000000,
      "year": 2025,
      "periodEnd": "2025-12-31"
    },
    "totalAssets": {
      "value": 14088000000,
      "year": 2025,
      "periodEnd": "2025-12-31"
    },
    "currentLiabilities": {
      "value": 887000000,
      "year": 2025,
      "periodEnd": "2025-12-31"
    },
    "totalLiabilities": null,
    "shareholdersEquity": {
      "value": 4838000000,
      "year": 2025,
      "periodEnd": "2025-12-31"
    },
    "operatingCashFlow": {
      "value": 2752000000,
      "year": 2025,
      "periodEnd": "2025-12-31"
    },
    "capex": {
      "value": 950000000,
      "year": 2025,
      "periodEnd": "2025-12-31"
    }
  },
  "fetchedAt": "2026-05-08T18:44:37.321Z"
}