{
  "ticker": "ESS",
  "name": "ESSEX PROPERTY TRUST, INC.",
  "cik": 920522,
  "fiscalYear": 2025,
  "metrics": {
    "revenue": {
      "value": 9381000,
      "year": 2025,
      "periodEnd": "2025-12-31"
    },
    "cogs": null,
    "grossProfit": {
      "value": 1318978000,
      "year": 2025,
      "periodEnd": "2025-12-31"
    },
    "operatingIncome": {
      "value": 899316000,
      "year": 2025,
      "periodEnd": "2025-12-31"
    },
    "netIncome": {
      "value": 390153000,
      "year": 2018,
      "periodEnd": "2018-12-31"
    },
    "currentAssets": null,
    "totalAssets": {
      "value": 13159009000,
      "year": 2025,
      "periodEnd": "2025-12-31"
    },
    "currentLiabilities": null,
    "totalLiabilities": {
      "value": 7422114000,
      "year": 2025,
      "periodEnd": "2025-12-31"
    },
    "shareholdersEquity": {
      "value": 5541372000,
      "year": 2025,
      "periodEnd": "2025-12-31"
    },
    "operatingCashFlow": {
      "value": 1074423000,
      "year": 2025,
      "periodEnd": "2025-12-31"
    },
    "capex": null
  },
  "fetchedAt": "2026-05-08T18:49:21.197Z"
}