{
  "ticker": "GEN",
  "name": "Gen Digital Inc.",
  "cik": 849399,
  "fiscalYear": 2025,
  "metrics": {
    "revenue": {
      "value": 3935000000,
      "year": 2025,
      "periodEnd": "2025-03-28"
    },
    "cogs": {
      "value": 776000000,
      "year": 2025,
      "periodEnd": "2025-03-28"
    },
    "grossProfit": {
      "value": 3159000000,
      "year": 2025,
      "periodEnd": "2025-03-28"
    },
    "operatingIncome": {
      "value": 1610000000,
      "year": 2025,
      "periodEnd": "2025-03-28"
    },
    "netIncome": {
      "value": 643000000,
      "year": 2025,
      "periodEnd": "2025-03-28"
    },
    "currentAssets": {
      "value": 1444000000,
      "year": 2025,
      "periodEnd": "2025-03-28"
    },
    "totalAssets": {
      "value": 15495000000,
      "year": 2025,
      "periodEnd": "2025-03-28"
    },
    "currentLiabilities": {
      "value": 2851000000,
      "year": 2025,
      "periodEnd": "2025-03-28"
    },
    "totalLiabilities": {
      "value": 13226000000,
      "year": 2025,
      "periodEnd": "2025-03-28"
    },
    "shareholdersEquity": {
      "value": 2269000000,
      "year": 2025,
      "periodEnd": "2025-03-28"
    },
    "operatingCashFlow": {
      "value": 1221000000,
      "year": 2025,
      "periodEnd": "2025-03-28"
    },
    "capex": {
      "value": 15000000,
      "year": 2025,
      "periodEnd": "2025-03-28"
    }
  },
  "fetchedAt": "2026-05-08T18:51:12.795Z"
}